wasabigeom.cpython-38-darwin.so
wasabi_geom-2.2.0.dist-info/RECORD
wasabi_geom-2.2.0.dist-info/LICENSE
wasabi_geom-2.2.0.dist-info/WHEEL
wasabi_geom-2.2.0.dist-info/top_level.txt
wasabi_geom-2.2.0.dist-info/METADATA
