Metadata-Version: 2.1
Name: wasabi-geom
Version: 2.2.0
Summary: 2D vector, line and polygon classes, and a spatial hash implementation
Home-page: https://github.com/lordmauve/wasabigeom
Author: Daniel Pope
Author-email: mauve@mauveweb.co.uk
Project-URL: Home, https://github.com/lordmauve/wasabigeom
Classifier: Development Status :: 5 - Production/Stable
Classifier: License :: OSI Approved :: BSD License
Classifier: Programming Language :: Python :: 3
License-File: LICENSE
Provides-Extra: dev
Requires-Dist: pytest; extra == "dev"
Requires-Dist: hypothesis; extra == "dev"
Requires-Dist: Sphinx>=2; extra == "dev"
Requires-Dist: numpy; extra == "dev"
Requires-Dist: pygame; extra == "dev"
